[{"line":1,"elements":[{"line":6,"name":"","description":"","type":"background","keyword":"Background","steps":[{"result":{"duration":297206600,"status":"passed"},"line":7,"name":"I am on the Open Savings Account page","match":{"location":"stepdefinitions.OpenSavingsAccountSteps.i_am_on_the_open_savings_account_page()"},"keyword":"Given "}]},{"start_timestamp":"2025-08-28T05:27:29.667Z","before":[{"result":{"duration":3355717100,"status":"passed"},"match":{"location":"hooks.Hooks.setUp(io.cucumber.java.Scenario)"}}],"line":10,"name":"Successfully submitting the savings account application with default test data","description":"","id":"open-savings-account-form;successfully-submitting-the-savings-account-application-with-default-test-data","after":[{"result":{"duration":2290477300,"status":"passed"},"match":{"location":"hooks.Hooks.tearDown(io.cucumber.java.Scenario)"}}],"type":"scenario","keyword":"Scenario","steps":[{"result":{"duration":2245809300,"status":"passed"},"line":11,"name":"I fill the form with default test data","match":{"location":"stepdefinitions.OpenSavingsAccountSteps.i_fill_the_form_with_default_test_data()"},"keyword":"When "},{"result":{"duration":311198500,"status":"passed"},"line":12,"name":"I click on the Submit Application button","match":{"location":"stepdefinitions.OpenSavingsAccountSteps.i_click_on_the_submit_application_button()"},"keyword":"And "},{"result":{"duration":15958600,"status":"passed"},"line":13,"name":"I should see a confirmation message \"Your Savings Account application has been submitted successfully!\"","match":{"arguments":[{"val":"\"Your Savings Account application has been submitted successfully!\"","offset":36}],"location":"stepdefinitions.OpenSavingsAccountSteps.i_should_see_a_confirmation_message(java.lang.String)"},"keyword":"Then "}],"tags":[{"name":"@PositiveScenario"}]}],"name":"Open Savings Account Form","description":"  As a user\n  I want to fill and submit the Open Savings Account form\n  So that I can apply for a new savings account","id":"open-savings-account-form","keyword":"Feature","uri":"file:src/test/resources/features/OpenSavingsAccountForm.feature","tags":[]}]